{
	"0": [
		"Court Warlock"
	],
	"1": [
		"Adventurer Group",
		"Eldritch Dragon Lord",
		"Ice Horror",
		"The Gravedigger"
	],
	"2": [
		"Blight Mariner",
		"Bone Overlord",
		"Tropical Desolator",
		"Vladrukh"
	],
	"3": [
		"Wrathful Archivist"
	],
	"5": [
		"Arbaziloth",
		"The Rootkraken"
	],
	"6": [
		"Mitmah Vanguard"
	],
	"7": [
		"Abyssador"
	],
	"8": [
		"Darkfang",
		"Gorzindel",
		"Urmahlullu the Weakened"
	],
	"9": [
		"Kusuma",
		"The Brainstealer"
	],
	"10": [
		"Sharpclaw",
		"Vemiath"
	],
	"11": [
		"Ahau",
		"Faceless Bane",
		"Goshnar’s Spite",
		"Katex Blood Tongue",
		"Lord Azaram",
		"Mazoran",
		"The False God",
		"The Mega Magmaoid",
		"The Pale Worm",
		"The Sandking",
		"The Scourge of Oblivion"
	],
	"12": [
		"Black Vixen",
		"Chagorz",
		"Essence of Malice",
		"Goshnar’s Cruelty",
		"Ichgahal",
		"Irgix the Flimsy",
		"King Zelos",
		"Lloyd",
		"Lokathmor",
		"Lord Retro",
		"Murcion",
		"Ragiaz",
		"Scarlett Etzel",
		"Sir Baeloc",
		"Tentugly",
		"The Monster",
		"Unaz the Mean",
		"Utua Stone Sting",
		"Vok the Freakish",
		"Zamulosh"
	],
	"13": [
		"Anomaly",
		"Brain Head",
		"Count Vlarkorth",
		"Deathstrike",
		"Dragon Pack",
		"Ekatrix",
		"Goshnar’s Hatred",
		"Razzagorn",
		"Srezz Yellow Eyes",
		"Tarbaz",
		"The Fear Feaster",
		"The Source of Corruption",
		"The Unarmored Voidborn"
	],
	"14": [
		"Amenef the Burning",
		"Ghulosh",
		"Gnomevil",
		"Lady Tenebris",
		"Magma Bubble",
		"Mazzinor",
		"Megasylvan Yselda",
		"Realityquake",
		"Shulgrax",
		"Sir Nictros",
		"Sister Hetai",
		"Soul of Dragonking Zyrtarch",
		"The Time Guardian",
		"The Winter Bloom",
		"Yirkas Blue Scales"
	],
	"15": [
		"Bloodback",
		"Duke Krule",
		"Goshnar’s Greed",
		"Goshnar’s Malice",
		"Melting Frozen Horror",
		"Outburst",
		"Thaian",
		"The Dread Maiden",
		"The Moonlight Aster",
		"The Unwelcome"
	],
	"16": [
		"Plagirath",
		"Ravenous Hunger",
		"Rupture",
		"The Blazing Rose",
		"The Souldespoiler",
		"Timira the Many-Headed"
	],
	"17": [
		"Brokul",
		"Eradicator",
		"Grand Master Oberon",
		"The Diamond Blossom",
		"The Enraged Thorn Knight",
		"The Flaming Orchid",
		"The Lily of Night",
		"The Nightmare Beast"
	],
	"18": [
		"Drume",
		"Neferi the Spy"
	],
	"19": [
		"Earl Osam",
		"Shadowpelt"
	],
	"21": [
		"Ratmiral Blackwhiskers"
	],
	"NaN": [
		"abyssador"
	]
}
