{
	"0": [
		"The Rootkraken"
	],
	"1": [
		"Abyssador"
	],
	"3": [
		"Mitmah Vanguard",
		"Vemiath"
	],
	"4": [
		"Dragon Pack",
		"Ichgahal",
		"Kusuma"
	],
	"5": [
		"Chagorz",
		"Gorzindel",
		"Goshnar’s Hatred",
		"Sir Baeloc",
		"The Brainstealer",
		"The Unarmored Voidborn"
	],
	"6": [
		"Anomaly",
		"Black Vixen",
		"Count Vlarkorth",
		"Essence of Malice",
		"Ghulosh",
		"Goshnar’s Cruelty",
		"Irgix the Flimsy",
		"Soul of Dragonking Zyrtarch",
		"Tarbaz",
		"The False God",
		"The Monster",
		"The Scourge of Oblivion",
		"Urmahlullu the Weakened"
	],
	"7": [
		"Ahau",
		"Darkfang",
		"Goshnar’s Spite",
		"Katex Blood Tongue",
		"King Zelos",
		"Lloyd",
		"Lord Azaram",
		"Mazoran",
		"Megasylvan Yselda",
		"Murcion",
		"Realityquake",
		"Srezz Yellow Eyes",
		"The Fear Feaster",
		"Utua Stone Sting",
		"Vok the Freakish",
		"Yirkas Blue Scales",
		"Zamulosh"
	],
	"8": [
		"Brain Head",
		"Faceless Bane",
		"Lady Tenebris",
		"Lord Retro",
		"Mazzinor",
		"Melting Frozen Horror",
		"Plagirath",
		"Ragiaz",
		"Scarlett Etzel",
		"Shulgrax",
		"Sister Hetai",
		"Tentugly",
		"Thaian",
		"The Mega Magmaoid",
		"The Pale Worm",
		"The Sandking",
		"The Source of Corruption",
		"Timira the Many-Headed"
	],
	"9": [
		"Amenef the Burning",
		"Bloodback",
		"Brokul",
		"Deathstrike",
		"Ekatrix",
		"Gnomevil",
		"Lokathmor",
		"Magma Bubble",
		"Razzagorn",
		"Sharpclaw",
		"The Dread Maiden",
		"The Moonlight Aster",
		"The Souldespoiler",
		"The Winter Bloom"
	],
	"10": [
		"Drume",
		"Goshnar’s Greed",
		"Outburst",
		"Rupture",
		"The Blazing Rose",
		"The Diamond Blossom",
		"The Lily of Night",
		"The Unwelcome",
		"Unaz the Mean"
	],
	"11": [
		"Duke Krule",
		"Goshnar’s Malice",
		"Ravenous Hunger",
		"Sir Nictros",
		"The Enraged Thorn Knight",
		"The Nightmare Beast",
		"The Time Guardian"
	],
	"12": [
		"Earl Osam",
		"Grand Master Oberon",
		"Neferi the Spy",
		"Ratmiral Blackwhiskers"
	],
	"13": [
		"Eradicator",
		"Shadowpelt",
		"The Flaming Orchid"
	]
}
